{
  "explorationState": "{\"version\":\"1.8\",\"activeSection\":\"\",\"sections\":{\"ReportSection5df63b15a8c10edb8b05\":{\"visualContainers\":{\"364d3c2d546cacccb155\":{\"singleVisual\":{\"visualType\":\"textbox\",\"mobileVcObjects\":{\"border\":[{\"properties\":{\"radius\":{\"expr\":{\"Literal\":{\"Value\":\"14D\"}}}}}]},\"mobileObjects\":{\"general\":[{\"properties\":{\"paragraphs\":[{\"textRuns\":[{\"value\":\"Public Trustee Resources:\",\"textStyle\":{\"fontWeight\":\"bold\",\"fontSize\":\"8pt\",\"textDecoration\":\"underline\"}}]},{\"textRuns\":[{\"value\":\"Douglas County Bidder Registration Form\",\"textStyle\":{\"fontSize\":\"8pt\",\"color\":\"#1d4ef3\"},\"url\":\"https://www.douglas.co.us/documents/bidder-registration.pdf/\"}]},{\"textRuns\":[{\"value\":\"Douglas County Foreclosure Sale Process\",\"textStyle\":{\"fontSize\":\"8pt\",\"color\":\"#1d4ef3\"},\"url\":\"https://www.douglas.co.us/public-trustee/foreclosure-sale-process/\"}]},{\"textRuns\":[{\"value\":\"Douglas County Public Trustee Website\",\"textStyle\":{\"fontSize\":\"8pt\",\"color\":\"#1d4ef3\"},\"url\":\"https://www.douglas.co.us/public-trustee/\"}]},{\"textRuns\":[{\"value\":\"Douglas County Public Trustee Forms\",\"textStyle\":{\"fontSize\":\"8pt\",\"color\":\"#1d4ef3\"},\"url\":\"https://www.douglas.co.us/public-trustee/foreclosure-forms-fees/\"}]},{\"textRuns\":[{\"value\":\"Foreclosure Timeline- At-A-Glance\",\"textStyle\":{\"fontSize\":\"8pt\",\"color\":\"#1d4ef3\"},\"url\":\"https://www.douglas.co.us/documents/foreclosure-timeline.pdf/\"}]},{\"textRuns\":[{\"value\":\"Foreclosure Search- Customer Feedback\",\"textStyle\":{\"fontSize\":\"8pt\",\"color\":\"#1d4ef3\"},\"url\":\"https://www.douglas.co.us/public-trustee/public-trustee-customer-feedback/\"}]},{\"textRuns\":[{\"value\":\"email:\",\"textStyle\":{\"fontSize\":\"8pt\",\"color\":\"#000000\"}},{\"value\":\" pubtrust@douglas.co.us\",\"textStyle\":{\"fontSize\":\"8pt\",\"color\":\"#1143f7\"}}]},{\"textRuns\":[{\"value\":\"\"}]},{\"textRuns\":[{\"value\":\"Other Douglas County Resources:\",\"textStyle\":{\"fontWeight\":\"bold\",\"fontSize\":\"8pt\",\"textDecoration\":\"underline\"}}]},{\"textRuns\":[{\"value\":\"Assessor\",\"textStyle\":{\"fontSize\":\"8pt\",\"color\":\"#1d4ef3\"},\"url\":\"https://www.douglas.co.us/assessor/#/\"}]},{\"textRuns\":[{\"value\":\"Clerk and Recorder\",\"textStyle\":{\"fontSize\":\"8pt\",\"color\":\"#1d4ef3\"},\"url\":\"https://www.douglas.co.us/recording/kiosk/\"}]},{\"textRuns\":[{\"value\":\"Treasurer- Tax Account Search\",\"textStyle\":{\"fontSize\":\"8pt\",\"color\":\"#1d4ef3\"},\"url\":\"https://apps.douglas.co.us/treasurer/treasurerweb/search.jsp?guest=true\"}]},{\"textRuns\":[{\"value\":\"Douglas County Human Services﻿\",\"textStyle\":{\"fontSize\":\"8pt\",\"color\":\"#1d4ef3\"},\"url\":\"https://www.douglas.co.us/human-services/\"}]},{\"textRuns\":[{\"value\":\"Douglas County Veterans Services\",\"textStyle\":{\"fontSize\":\"8pt\",\"color\":\"#1d4ef3\"},\"url\":\"https://www.douglas.co.us/veterans-service-office/resources-veterans/\"}]},{\"textRuns\":[{\"value\":\"Douglas County Housing Partnership\",\"textStyle\":{\"fontSize\":\"8pt\",\"color\":\"#1d4ef3\"},\"url\":\"https://douglascountyhousingpartnership.org/\"}]},{\"textRuns\":[{\"value\":\"Douglas County Sheriff Civil Sales\",\"textStyle\":{\"fontSize\":\"8pt\",\"color\":\"#1d4ef3\"},\"url\":\"https://www.dcsheriff.net/sheriffs-office/divisions/support-services/civil/sheriffs-civil-sales/\"}]},{\"textRuns\":[{\"value\":\"\"}]},{\"textRuns\":[{\"value\":\"Additional Resources:\",\"textStyle\":{\"fontWeight\":\"bold\",\"fontSize\":\"8pt\",\"textDecoration\":\"underline\"}}]},{\"textRuns\":[{\"value\":\"Colorado Attorney General\",\"textStyle\":{\"fontSize\":\"8pt\",\"color\":\"#1d4ef3\"},\"url\":\"https://coag.gov/\"}]},{\"textRuns\":[{\"value\":\"Colorado Housing Connects\",\"textStyle\":{\"fontSize\":\"8pt\",\"color\":\"#1d4ef3\"},\"url\":\"http://coloradohousingconnects.org/homeowners-i-need-help-avoiding-foreclosure/\"}]},{\"textRuns\":[{\"value\":\"Colorado Department of Local Affairs\",\"textStyle\":{\"fontSize\":\"8pt\",\"color\":\"#1d4ef3\"},\"url\":\"https://cdola.colorado.gov/\"}]},{\"textRuns\":[{\"value\":\"Federal Consumer Financial Protectio\",\"textStyle\":{\"fontSize\":\"8pt\",\"color\":\"#1d4ef3\"},\"url\":\"https://www.consumerfinance.gov/\"},{\"value\":\"n\",\"textStyle\":{\"fontSize\":\"9pt\",\"color\":\"#1d4ef3\"},\"url\":\"https://www.consumerfinance.gov/\"}]}]}}]}}},\"2ea018d2005ac0e3c92e\":{\"singleVisual\":{\"visualType\":\"textbox\",\"mobileObjects\":{\"general\":[{\"properties\":{\"paragraphs\":[{\"textRuns\":[{\"value\":\"To View Latest Weekly Sales List Data:\",\"textStyle\":{\"fontSize\":\"8pt\"}}],\"horizontalTextAlignment\":\"center\"},{\"textRuns\":[{\"value\":\"On Mobile, Pull-down page to refresh\",\"textStyle\":{\"fontSize\":\"8pt\"}}],\"horizontalTextAlignment\":\"center\"}]}}]}}}}},\"ReportSection931a99d09acdbb270b41\":{\"visualContainers\":{\"e744e562230eabb8c190\":{\"singleVisual\":{\"visualType\":\"textbox\",\"mobileObjects\":{\"general\":[{\"properties\":{\"paragraphs\":[{\"textRuns\":[{\"value\":\"General Questions:\",\"textStyle\":{\"fontWeight\":\"bold\",\"fontFamily\":\"Calibri\",\"fontSize\":\"12pt\",\"textDecoration\":\"underline\",\"color\":\"#000000\"}}]},{\"textRuns\":[{\"value\":\"\"}]},{\"textRuns\":[{\"value\":\"When and where is the Public Trustee sale conducted? How can I find which properties are actually going to sale each week?\",\"textStyle\":{\"fontWeight\":\"bold\",\"fontFamily\":\"Calibri\",\"fontSize\":\"11pt\",\"textDecoration\":\"underline\",\"color\":\"#117395\"}},{\"value\":\" \",\"textStyle\":{\"fontWeight\":\"bold\",\"fontFamily\":\"Calibri\",\"fontSize\":\"11pt\",\"color\":\"#0c4d63\"}}]},{\"textRuns\":[{\"value\":\"Sales are held, via a public auction, on Wednesday at 10:00 a.m. in the Philip S Miller Hearing Room at 100 Third Street in Castle Rock. To check what sales are scheduled, consult the \",\"textStyle\":{\"fontFamily\":\"Calibri\",\"fontSize\":\"11pt\"}},{\"value\":\"Weekly Sales List- Bid Received Live\",\"textStyle\":{\"fontFamily\":\"Calibri\",\"fontSize\":\"11pt\",\"color\":\"#141dd6\"},\"url\":\"https://pubreports.douglas.co.us/Home/Index/ForeclosureWeeklySales\"},{\"value\":\" report.\"},{\"value\":\" \",\"textStyle\":{\"fontFamily\":\"Calibri\",\"fontSize\":\"11pt\"}},{\"value\":\"If no properties are displayed, there is no sale\",\"textStyle\":{\"fontFamily\":\"Calibri\",\"fontStyle\":\"italic\",\"fontSize\":\"11pt\"}},{\"value\":\". Properties that are displayed, the starting bid will be displayed in the column labeled: Bid From the Lender. \",\"textStyle\":{\"fontFamily\":\"Calibri\",\"fontSize\":\"11pt\"}}]},{\"textRuns\":[{\"value\":\"PLEASE NOTE:\",\"textStyle\":{\"fontFamily\":\"Calibri\",\"fontSize\":\"11pt\",\"textDecoration\":\"underline\"}},{\"value\":\"  Sales may be pulled, up to 9:59, the day of sale. Please refresh the Weekly Sales List- Bid Received Live report for live and up to date information. \",\"textStyle\":{\"fontFamily\":\"Calibri\",\"fontSize\":\"11pt\"}}]},{\"textRuns\":[{\"value\":\"\"}]},{\"textRuns\":[{\"value\":\"What types of funds are necessary to bid at the Public Trustee sale?\",\"textStyle\":{\"fontWeight\":\"bold\",\"fontFamily\":\"Calibri\",\"fontSize\":\"11pt\",\"textDecoration\":\"underline\",\"color\":\"#117395\"}},{\"value\":\"  \",\"textStyle\":{\"fontWeight\":\"bold\",\"fontFamily\":\"Calibri\",\"fontSize\":\"11pt\",\"color\":\"#117395\"}}]},{\"textRuns\":[{\"value\":\"Certified funds, equal to the lender’s minimum bid plus $50, are required and must be presented to bid.  Funds must be payable to the Douglas County Public Trustee. Bidders may not join the auction until certified minimum bid requirements are met. (e.g., if the lender’s written bid is $100,000.00, certified funds in the minimum amount of $100,0\",\"textStyle\":{\"fontFamily\":\"Calibri\",\"fontSize\":\"11pt\",\"color\":\"#13130c\"}},{\"value\":\"50\",\"textStyle\":{\"fontFamily\":\"Calibri\",\"fontSize\":\"11pt\",\"textDecoration\":\"underline\",\"color\":\"#13130c\"}},{\"value\":\".00 must \",\"textStyle\":{\"fontFamily\":\"Calibri\",\"fontSize\":\"11pt\",\"color\":\"#13130c\"}},{\"value\":\"be presented)\",\"textStyle\":{\"fontFamily\":\"Calibri\",\"fontSize\":\"11pt\"}},{\"value\":\". \",\"textStyle\":{\"fontFamily\":\"Calibri\"}}]},{\"textRuns\":[{\"value\":\"\"}]},{\"textRuns\":[{\"value\":\"Why was a foreclosure auction postponed for a particular property?\",\"textStyle\":{\"fontWeight\":\"bold\",\"fontFamily\":\"Calibri\",\"fontSize\":\"11pt\",\"textDecoration\":\"underline\",\"color\":\"#117395\"}}]},{\"textRuns\":[{\"value\":\"Not every house will go to auction. Some properties will be continued (postponed) week to week due to a bankruptcy stay, a pending cure, a request from the lender's attorney, or other reasons\",\"textStyle\":{\"fontFamily\":\"Calibri\",\"fontSize\":\"11pt\"}},{\"value\":\". \",\"textStyle\":{\"fontFamily\":\"Calibri\",\"fontSize\":\"14.6667px\"}},{\"value\":\"Also, if we do not receive a written bid from the lender by 12:00 noon two business days prior to the scheduled sale date, we will automatically continue the sale one week. \",\"textStyle\":{\"fontFamily\":\"Calibri\",\"fontSize\":\"11pt\"}}]},{\"textRuns\":[{\"value\":\"\"}]},{\"textRuns\":[{\"value\":\"Where do I obtain information about other liens against properties?\",\"textStyle\":{\"fontWeight\":\"bold\",\"fontFamily\":\"Calibri\",\"fontSize\":\"11pt\",\"textDecoration\":\"underline\",\"color\":\"#117395\"}},{\"value\":\"  \",\"textStyle\":{\"fontWeight\":\"bold\",\"fontFamily\":\"Calibri\",\"fontSize\":\"11pt\",\"color\":\"#117395\"}}]},{\"textRuns\":[{\"value\":\"Liens recorded against a Douglas County property may be obtained by contacting a Title Company or researching through Douglas County Clerk and Recorder.\",\"textStyle\":{\"fontFamily\":\"Calibri\",\"fontSize\":\"11pt\"}},{\"value\":\" \",\"textStyle\":{\"fontFamily\":\"Calibri\",\"fontSize\":\"9pt\"}},{\"value\":\"Please be aware, there might be other liens outside of Douglas County. \",\"textStyle\":{\"fontFamily\":\"Calibri\",\"fontSize\":\"11pt\"}},{\"value\":\"PLEASE NOTE:\",\"textStyle\":{\"fontFamily\":\"Calibri\",\"fontSize\":\"11pt\",\"textDecoration\":\"underline\"}},{\"value\":\" The Public Trustee does not know if the lien in foreclosure is the first lien. Please conduct due diligence and your own research before a sale.\",\"textStyle\":{\"fontFamily\":\"Calibri\",\"fontSize\":\"11pt\"}}]},{\"textRuns\":[{\"value\":\"\"}]},{\"textRuns\":[{\"value\":\"What does Hold Issue mean?\",\"textStyle\":{\"fontWeight\":\"bold\",\"fontFamily\":\"Calibri\",\"fontSize\":\"11pt\",\"textDecoration\":\"underline\",\"color\":\"#117395\"}},{\"value\":\" \",\"textStyle\":{\"fontWeight\":\"bold\",\"fontFamily\":\"Calibri\",\"fontSize\":\"11pt\",\"color\":\"#117395\"}}]},{\"textRuns\":[{\"value\":\"An issue that has temporarily stopped the foreclosure process -- typically, a bankruptcy. \",\"textStyle\":{\"fontFamily\":\"Calibri\",\"fontSize\":\"11pt\"}}]},{\"textRuns\":[{\"value\":\"\"}]},{\"textRuns\":[{\"value\":\"If I am the successful bid winner, how long do I have to bring you the full amount of my bid?\",\"textStyle\":{\"fontWeight\":\"bold\",\"fontFamily\":\"Calibri\",\"fontSize\":\"11pt\",\"textDecoration\":\"underline\",\"color\":\"#117395\"}},{\"value\":\"  \",\"textStyle\":{\"fontWeight\":\"bold\",\"fontFamily\":\"Calibri\",\"fontSize\":\"11pt\",\"color\":\"#117395\"}}]},{\"textRuns\":[{\"value\":\"Upon request, the Public Trustee may grant permission to a winning bidder to obtain additional certified funds, beyond the minimum brought to the sale, within (2) hours from the conclusion of the foreclosure sale. Otherwise, certified funds that exceed the amount of the winning bid will be refunded after four (4) business days. The check will be mailed to the winning bidder- unless a request is made on the \",\"textStyle\":{\"fontFamily\":\"Calibri\",\"fontSize\":\"11pt\"}},{\"value\":\"Bidder Registration\",\"textStyle\":{\"fontFamily\":\"Calibri\",\"fontSize\":\"11pt\",\"color\":\"#152ed3\"},\"url\":\"https://www.douglas.co.us/documents/bidder-registration.pdf/\"},{\"value\":\" \",\"textStyle\":{\"fontFamily\":\"Calibri\",\"fontSize\":\"11pt\",\"color\":\"#092398\"},\"url\":\"https://www.douglas.co.us/documents/bidder-registration.pdf/\"},{\"value\":\"sheet for it to be held for pick-up. \",\"textStyle\":{\"fontFamily\":\"Calibri\",\"fontSize\":\"11pt\"}}]},{\"textRuns\":[{\"value\":\"\"}]},{\"textRuns\":[{\"value\":\"What does Foreclosure Status mean?\",\"textStyle\":{\"fontWeight\":\"bold\",\"fontFamily\":\"Calibri\",\"fontSize\":\"11pt\",\"textDecoration\":\"underline\",\"color\":\"#117395\"}}]},{\"textRuns\":[{\"value\":\"Pre-Sale\",\"textStyle\":{\"fontFamily\":\"Calibri\",\"fontSize\":\"11pt\",\"textDecoration\":\"underline\"}},{\"value\":\": Foreclosures that are open but have not gone to sale yet. \",\"textStyle\":{\"fontFamily\":\"Calibri\",\"fontSize\":\"11pt\"}}],\"listType\":\"bullet\"},{\"textRuns\":[{\"value\":\"Post-Sale\",\"textStyle\":{\"fontFamily\":\"Calibri\",\"fontSize\":\"11pt\",\"textDecoration\":\"underline\"}},{\"value\":\": If the property was sold at auction, the status will be Post-Sale and is currently in the redemption period. \",\"textStyle\":{\"fontFamily\":\"Calibri\",\"fontSize\":\"11pt\"}}],\"listType\":\"bullet\"},{\"textRuns\":[{\"value\":\"Closed:\",\"textStyle\":{\"fontFamily\":\"Calibri\",\"fontSize\":\"11pt\",\"textDecoration\":\"underline\"}},{\"value\":\" Foreclosures that are closed through withdrawal, redemption, or deeded. (If a file is closed, it means it is no longer in foreclosure)\",\"textStyle\":{\"fontFamily\":\"Calibri\",\"fontSize\":\"11pt\"}}],\"listType\":\"bullet\"},{\"textRuns\":[{\"value\":\"\"}]},{\"textRuns\":[{\"value\":\"I just purchased a property at the Public Trustee's Auction. Where do I pick up the keys to the house, and when can I move in?\",\"textStyle\":{\"fontWeight\":\"bold\",\"fontFamily\":\"Calibri\",\"fontSize\":\"11pt\",\"textDecoration\":\"underline\",\"color\":\"#117395\"}}]},{\"textRuns\":[{\"value\":\"Please consult a real estate attorney to determine when it is legal to enter a home purchased at auction through the Public Trustee. The Public Trustee does not have the keys to any properties.\",\"textStyle\":{\"fontFamily\":\"Calibri\",\"fontSize\":\"11pt\"}}]},{\"textRuns\":[{\"value\":\"\"}]},{\"textRuns\":[{\"value\":\"How do I find if a specific property is in foreclosure?\",\"textStyle\":{\"fontWeight\":\"bold\",\"fontFamily\":\"Calibri\",\"fontSize\":\"11pt\",\"textDecoration\":\"underline\",\"color\":\"#117395\"}},{\"value\":\"  \",\"textStyle\":{\"fontWeight\":\"bold\",\"fontFamily\":\"Calibri\",\"fontSize\":\"11pt\",\"color\":\"#117395\"}}]},{\"textRuns\":[{\"value\":\"There are many ways to search for a specific property in foreclosure. Go to Quick Search and search by: a PT #, a property Address, Borrower Name, Attorney File Number, etc. - To search a property that was previously in foreclosure, and now closed, please press the Reset/View All button, located under Popular Reports, and proceed with your search in the Search bar.\",\"textStyle\":{\"fontFamily\":\"Calibri\",\"fontSize\":\"11pt\",\"color\":\"#13130c\"}}]},{\"textRuns\":[{\"value\":\"\"}]},{\"textRuns\":[{\"value\":\"Can you tell me all the properties in foreclosure?\",\"textStyle\":{\"fontWeight\":\"bold\",\"fontFamily\":\"Calibri\",\"fontSize\":\"11pt\",\"textDecoration\":\"underline\",\"color\":\"#117395\"}},{\"value\":\"  \",\"textStyle\":{\"fontWeight\":\"bold\",\"fontFamily\":\"Calibri\",\"fontSize\":\"11pt\",\"color\":\"#117395\"}}]},{\"textRuns\":[{\"value\":\"To locate all the properties in foreclosure, please consult our \",\"textStyle\":{\"fontFamily\":\"Calibri\",\"fontSize\":\"11pt\",\"color\":\"#13130c\"}},{\"value\":\"Quick Search, or Advanced Search, and press Properties in Foreclosure\",\"textStyle\":{\"fontFamily\":\"Calibri\",\"fontSize\":\"11pt\"}},{\"value\":\". Foreclosure is a complex process, and we suggest you contact your legal advisor if you have concerns or questions about a specific property, or the foreclosure process.  \",\"textStyle\":{\"fontFamily\":\"Calibri\",\"fontSize\":\"11pt\",\"color\":\"#13130c\"}}]},{\"textRuns\":[{\"value\":\"\"}]},{\"textRuns\":[{\"value\":\"How often is the Foreclosure Search updated?\",\"textStyle\":{\"fontWeight\":\"bold\",\"fontFamily\":\"Calibri\",\"fontSize\":\"11pt\",\"textDecoration\":\"underline\",\"color\":\"#117395\"}},{\"value\":\" \",\"textStyle\":{\"fontWeight\":\"bold\",\"fontFamily\":\"Calibri\",\"fontSize\":\"11pt\",\"color\":\"#117395\"}},{\"value\":\" \",\"textStyle\":{\"fontWeight\":\"bold\",\"fontFamily\":\"Calibri\",\"fontSize\":\"11pt\",\"color\":\"#2379a9\"}}]},{\"textRuns\":[{\"value\":\"The foreclosure reports are updated regularly and will display when the data was last updated. The \",\"textStyle\":{\"fontFamily\":\"Calibri\",\"fontSize\":\"11pt\",\"color\":\"#13130c\"}},{\"value\":\"Weekly Sales List- Bid Received Live\",\"textStyle\":{\"fontFamily\":\"Calibri\",\"fontSize\":\"11pt\",\"color\":\"#0f45f6\"},\"url\":\"https://pubreports.douglas.co.us/Home/Index/ForeclosureWeeklySales\"},{\"value\":\" report offers real time live data for Scheduled Sales and will display when the data was last updated, and the page was refreshed. \"}]},{\"textRuns\":[{\"value\":\"\"}]},{\"textRuns\":[{\"value\":\"Does the Office of the Public Trustee conduct seminars about the foreclosure process?\",\"textStyle\":{\"fontWeight\":\"bold\",\"fontFamily\":\"Calibri\",\"fontSize\":\"11pt\",\"textDecoration\":\"underline\",\"color\":\"#117395\"}},{\"value\":\"  \",\"textStyle\":{\"fontWeight\":\"bold\",\"fontFamily\":\"Calibri\",\"fontSize\":\"11pt\",\"color\":\"#117395\"}}]},{\"textRuns\":[{\"value\":\"No. The Public Trustee's office does not conduct seminars for potential investors, or curious observers. Instead, the office has compiled information on this foreclosure search and our \",\"textStyle\":{\"fontFamily\":\"Calibri\",\"fontSize\":\"11pt\",\"color\":\"black\"}},{\"value\":\"website\",\"textStyle\":{\"fontFamily\":\"Calibri\",\"fontSize\":\"11pt\",\"color\":\"#1449f5\"},\"url\":\"https://www.douglas.co.us/public-trustee/\"},{\"value\":\" as a tool to learn about the foreclosure process. \",\"textStyle\":{\"fontFamily\":\"Calibri\",\"fontSize\":\"11pt\",\"color\":\"black\"}}]},{\"textRuns\":[{\"value\":\"\"}]},{\"textRuns\":[{\"value\":\"What is a Notice of Election and Demand (NED)?\",\"textStyle\":{\"fontWeight\":\"bold\",\"fontFamily\":\"Calibri\",\"fontSize\":\"11pt\",\"textDecoration\":\"underline\",\"color\":\"#117395\"}},{\"value\":\"  \",\"textStyle\":{\"fontWeight\":\"bold\",\"fontFamily\":\"Calibri\",\"fontSize\":\"11pt\",\"color\":\"#117395\"}}]},{\"textRuns\":[{\"value\":\"Recording of the Notice of Election and Demand (NED) starts \",\"textStyle\":{\"fontFamily\":\"Calibri\",\"fontSize\":\"11pt\",\"color\":\"black\"}},{\"value\":\"the foreclosure process with the Public Trustee and governs the statutes that the foreclosure will follow\",\"textStyle\":{\"fontFamily\":\"Calibri\",\"fontSize\":\"10.5pt\",\"color\":\"#14140c\"}},{\"value\":\". A sale date will be established and scheduled 110-125 days from the date of recording the NED or 215-230 days if the property is agriculture. \",\"textStyle\":{\"fontFamily\":\"Calibri\",\"fontSize\":\"11pt\",\"color\":\"black\"}}]},{\"textRuns\":[{\"value\":\"\"}]},{\"textRuns\":[{\"value\":\"Are Taxpayer dollars used to fund the Public Trustee's Office?\",\"textStyle\":{\"fontWeight\":\"bold\",\"fontFamily\":\"Calibri\",\"fontSize\":\"11pt\",\"textDecoration\":\"underline\",\"color\":\"#117395\"}},{\"value\":\" \",\"textStyle\":{\"fontWeight\":\"bold\",\"fontFamily\":\"Calibri\",\"fontSize\":\"11pt\",\"color\":\"#117395\"}},{\"value\":\" \",\"textStyle\":{\"fontWeight\":\"bold\",\"fontFamily\":\"Calibri\",\"fontSize\":\"11pt\",\"color\":\"#2379a9\"}}]},{\"textRuns\":[{\"value\":\"No tax money is used to operate the Public Trustee's office. This office is funded by user fees. (C.R.S. 38-37-101(1))\",\"textStyle\":{\"fontFamily\":\"Calibri\",\"fontSize\":\"11pt\",\"color\":\"#13130c\"}}]},{\"textRuns\":[{\"value\":\" \",\"textStyle\":{\"fontFamily\":\"Calibri\",\"fontSize\":\"11pt\",\"color\":\"#2e74b5\"}}]},{\"textRuns\":[{\"value\":\"\"}]},{\"textRuns\":[{\"value\":\" *\",\"textStyle\":{\"fontFamily\":\"Calibri\",\"fontSize\":\"11pt\"}},{\"value\":\"C.R.S. 38-37-108: All moneys payable to a public trustee at any foreclosure sale under the provisions of this article or upon redemption or cure pursuant to article 38 of this title shall be in the form of cash, electronic transfer to an account of the public trustee available for such purpose or a certified check, cashier’s check, or teller’s check, or draft denominated as an official check that is a teller’s check or a cashier’s check as those terms are defined in and governed by the “Uniform Commercial Code”, title 4, C.R.S., made payable to the public trustee and certified or issued by a state-charted bank, savings and loan association, or credit union licensed to do business in the state of Colorado or a federally chartered bank, savings bank, or credit union.\",\"textStyle\":{\"fontFamily\":\"Calibri\",\"fontStyle\":\"italic\",\"fontSize\":\"9pt\"}}]},{\"textRuns\":[{\"value\":\"\"}]},{\"textRuns\":[{\"value\":\"Are you in Foreclosure FAQ’s:\",\"textStyle\":{\"fontWeight\":\"bold\",\"fontFamily\":\"Calibri\",\"fontSize\":\"12pt\",\"textDecoration\":\"underline\"}}]},{\"textRuns\":[{\"value\":\"\"}]},{\"textRuns\":[{\"value\":\"How do I find if my property is in foreclosure?\",\"textStyle\":{\"fontWeight\":\"bold\",\"fontFamily\":\"Calibri\",\"fontSize\":\"11pt\",\"textDecoration\":\"underline\",\"color\":\"#117395\"}},{\"value\":\"  \",\"textStyle\":{\"fontWeight\":\"bold\",\"fontFamily\":\"Calibri\",\"fontSize\":\"11pt\",\"color\":\"#117395\"}}]},{\"textRuns\":[{\"value\":\"Go to Quick Search and search by: a PT #, Borrower Last Name, a Property Address, an Attorney File Number, etc.  \",\"textStyle\":{\"fontFamily\":\"Calibri\",\"fontSize\":\"11pt\",\"color\":\"#13130c\"}}]},{\"textRuns\":[{\"value\":\"\"}]},{\"textRuns\":[{\"value\":\"How do I find what I owe to stop the foreclosure sale of my house?\",\"textStyle\":{\"fontWeight\":\"bold\",\"fontFamily\":\"Calibri\",\"fontSize\":\"11pt\",\"textDecoration\":\"underline\",\"color\":\"#117395\"}},{\"value\":\" \",\"textStyle\":{\"fontWeight\":\"bold\",\"fontFamily\":\"Calibri\",\"fontSize\":\"11pt\",\"color\":\"#117395\"}},{\"value\":\" \",\"textStyle\":{\"fontFamily\":\"Calibri\",\"fontSize\":\"11pt\",\"color\":\"#117395\"}}]},{\"textRuns\":[{\"value\":\"If you feel you may be able to obtain sufficient funds to cure the default (get caught up to date on your payments), you may file a \",\"textStyle\":{\"fontFamily\":\"Calibri\",\"fontSize\":\"11pt\"}},{\"value\":\"Notice of\",\"textStyle\":{\"fontFamily\":\"Calibri\",\"fontSize\":\"11pt\",\"color\":\"#141dd6\"},\"url\":\"https://www.douglas.co.us/documents/notice-of-intent-to-cure.pdf/\"},{\"value\":\" \",\"textStyle\":{\"fontFamily\":\"Calibri\",\"fontSize\":\"11pt\",\"color\":\"#141dd6\"}},{\"value\":\"Intent to Cure\",\"textStyle\":{\"fontFamily\":\"Calibri\",\"fontSize\":\"11pt\",\"color\":\"#141dd6\"},\"url\":\"https://www.douglas.co.us/documents/notice-of-intent-to-cure.pdf/\"},{\"value\":\". This form may be emailed to our office at \",\"textStyle\":{\"fontFamily\":\"Calibri\",\"fontSize\":\"11pt\"}},{\"value\":\"pubtrust@douglas.co.us\",\"textStyle\":{\"fontFamily\":\"Calibri\",\"fontSize\":\"11pt\",\"color\":\"#152ed3\"},\"url\":\"mailto:pubtrust@douglas.co.us\"},{\"value\":\". \",\"textStyle\":{\"fontFamily\":\"Calibri\",\"fontSize\":\"13.3333px\"}},{\"value\":\"Per law (C.R.S.) \",\"textStyle\":{\"fontFamily\":\"Calibri\",\"fontSize\":\"11pt\"}},{\"value\":\"38-38-104)\",\"textStyle\":{\"fontFamily\":\"Calibri\",\"fontSize\":\"14.6667px\"}},{\"value\":\", in order to preserve your right to cure, this notice must be filed with the Public Trustee’s Office at least 15 calendar days prior to the date of sale, or the first scheduled date of sale, or any later date to which the sale is continued. If the sale date is continued to a later date, the deadline to file a notice of intent to cure by those parties entitled to cure is also extended.  The Public Trustee will notify the attorney for the lender, and they will provide an amount necessary to cure the default. We will notify you immediately when we receive the information from the attorney. Also, you should contact the Douglas County Housing Partnership at 303.784.7856 or your lender to determine if foreclosure mitigation/loan modification services are available to you. \",\"textStyle\":{\"fontFamily\":\"Calibri\",\"fontSize\":\"11pt\"}}]},{\"textRuns\":[{\"value\":\" \",\"textStyle\":{\"fontFamily\":\"Calibri\",\"fontSize\":\"9pt\"}}]},{\"textRuns\":[{\"value\":\"What happens once I have filed an Intent to Cure with the Public Trustee?\",\"textStyle\":{\"fontWeight\":\"bold\",\"fontFamily\":\"Calibri\",\"fontSize\":\"11pt\",\"color\":\"#117395\"},\"url\":\"https://www.denvergov.org/content/denvergov/en/denver-office-of-the-clerk-and-recorder/foreclosures/frequently-asked-questions.html#2cbc7e57-7a69-427e-90d5-502c9c31d6cd\"}]},{\"textRuns\":[{\"value\":\"Please do not expect to receive the cure statement immediately after filing this form. We must request information from the lender’s attorney. The cure statement is due back to us within 10 business days of our request, or eight calendar days prior to the scheduled sale date, whichever is sooner. If the Intent to Cure is filed after the deadline, the foreclosing party has no obligation to provide a cure statement. If the Intent to Cure is filed timely and prior to the deadline, the property will not be sold until after the lender's attorney has provided a cure statement to the Public Trustee.\",\"textStyle\":{\"fontFamily\":\"Calibri\",\"fontSize\":\"14.6667px\"}}]},{\"textRuns\":[{\"value\":\"\"}]},{\"textRuns\":[{\"value\":\"\"}]},{\"textRuns\":[{\"value\":\"I received a foreclosure notice from you in the mail. Do I need \",\"textStyle\":{\"fontWeight\":\"bold\",\"fontFamily\":\"Calibri\",\"fontSize\":\"11pt\",\"textDecoration\":\"underline\",\"color\":\"#117395\"}},{\"value\":\"to move?\",\"textStyle\":{\"fontWeight\":\"bold\",\"fontFamily\":\"Calibri\",\"textDecoration\":\"underline\",\"color\":\"#117395\"}},{\"value\":\"  \",\"textStyle\":{\"fontWeight\":\"bold\",\"fontFamily\":\"Calibri\",\"fontSize\":\"11pt\",\"color\":\"#117395\"}}]},{\"textRuns\":[{\"value\":\"You still own the home and have the rights and obligations of a homeowner until the property has gone to sale and has been deeded to a new entity. If you do not move out after the foreclosure sale, you may be subject to eviction proceedings by the new owner of the property. \",\"textStyle\":{\"fontFamily\":\"Calibri\",\"fontSize\":\"11pt\"}}]},{\"textRuns\":[{\"value\":\" \",\"textStyle\":{\"fontFamily\":\"Calibri\",\"fontSize\":\"11pt\"}}]},{\"textRuns\":[{\"value\":\"Will I receive a notice if my house is sold at the foreclosure sale?\",\"textStyle\":{\"fontWeight\":\"bold\",\"fontFamily\":\"Calibri\",\"fontSize\":\"11pt\",\"textDecoration\":\"underline\",\"color\":\"#117395\"}},{\"value\":\"  \",\"textStyle\":{\"fontFamily\":\"Calibri\",\"fontSize\":\"11pt\",\"color\":\"#117395\"}}]},{\"textRuns\":[{\"value\":\"No. You will receive a second foreclosure notice from us on or about 60 days prior to the first scheduled sale of the property. No further notices will be sent. The scheduled sale date can be continued by your lender. Please check our \",\"textStyle\":{\"fontFamily\":\"Calibri\",\"fontSize\":\"11pt\",\"color\":\"#13130c\"}},{\"value\":\"Quick Search \",\"textStyle\":{\"fontFamily\":\"Calibri\",\"fontSize\":\"11pt\"}},{\"value\":\"for up-to-date information.\",\"textStyle\":{\"fontFamily\":\"Calibri\",\"fontSize\":\"11pt\",\"color\":\"#13130c\"}}]}]}}]}}}}}}}"
}